unrollcuda/__init__.py
unrollcuda/unrollcuda.py
unrollcuda-0.0.7.dist-info/METADATA
unrollcuda-0.0.7.dist-info/WHEEL
unrollcuda-0.0.7.dist-info/licenses/LICENSE
unrollcuda-0.0.7.dist-info/RECORD
