Metadata-Version: 2.1
Name: unrollcuda
Version: 0.0.7
Summary: Loop unrolling and batching for CUDA
Project-URL: Homepage, https://github.com/format37/unrollcuda
Project-URL: Bug Tracker, https://github.com/format37/unrollcuda/issues
Author-email: Aleksei Iurasov <format37@gmail.com>
License-File: LICENSE
Classifier: License :: OSI Approved :: Apache Software License
Classifier: Operating System :: OS Independent
Classifier: Programming Language :: Python :: 3
Requires-Python: >=3.8
Requires-Dist: numpy
Requires-Dist: pycuda
